README.txt
buildout.cfg
setup.cfg
setup.py
collective/__init__.py
collective.kssinline.egg-info/PKG-INFO
collective.kssinline.egg-info/SOURCES.txt
collective.kssinline.egg-info/dependency_links.txt
collective.kssinline.egg-info/entry_points.txt
collective.kssinline.egg-info/namespace_packages.txt
collective.kssinline.egg-info/not-zip-safe
collective.kssinline.egg-info/requires.txt
collective.kssinline.egg-info/top_level.txt
collective/kssinline/README.txt
collective/kssinline/TODO.txt
collective/kssinline/__init__.py
collective/kssinline/config.py
collective/kssinline/configure.zcml
collective/kssinline/kss.zcml
collective/kssinline/override.py
collective/kssinline/overrides.zcml
collective/kssinline/profiles.zcml
collective/kssinline/refresh.txt
collective/kssinline/setuphandlers.py
collective/kssinline/tests.py
collective/kssinline/tool.gif
collective/kssinline/browser/__init__.py
collective/kssinline/browser/configure.zcml
collective/kssinline/browser/interfaces.py
collective/kssinline/browser/kssview.py
collective/kssinline/browser/adapters/__init__.py
collective/kssinline/browser/adapters/configure.zcml
collective/kssinline/browser/adapters/links.py
collective/kssinline/browser/resources/__init__.py
collective/kssinline/browser/resources/configure.zcml
collective/kssinline/browser/resources/edit_icon.gif
collective/kssinline/browser/utilities/__init__.py
collective/kssinline/browser/utilities/configure.zcml
collective/kssinline/browser/utilities/links.py
collective/kssinline/browser/viewlets/__init__.py
collective/kssinline/browser/viewlets/calendar.pt
collective/kssinline/browser/viewlets/calendar.py
collective/kssinline/browser/viewlets/configure.zcml
collective/kssinline/browser/viewlets/links.pt
collective/kssinline/browser/viewlets/links.py
collective/kssinline/browser/viewlets/popup.pt
collective/kssinline/browser/viewlets/popup.py
collective/kssinline/browser/views/__init__.py
collective/kssinline/browser/views/configure.zcml
collective/kssinline/browser/views/foldercontents.pt
collective/kssinline/browser/views/foldercontents.py
collective/kssinline/browser/views/table.pt
collective/kssinline/browser/views/tableview.py
collective/kssinline/examples/__init__.py
collective/kssinline/examples/configure.zcml
collective/kssinline/examples/demo.pt
collective/kssinline/examples/adapters/__init__.py
