Metadata-Version: 1.0
Name: collective.kssinline
Version: 0.9.4
Summary: Edit and create content without navigating away from listings
Home-page: UNKNOWN
Author: Hedley Roos
Author-email: hedley@upfrontsystems.co.za
License: GPL
Platform: UNKNOWN
Classifier: Framework :: Plone
Classifier: Framework :: Zope2
Classifier: Framework :: Zope3
Classifier: Programming Language :: Python
Classifier: Topic :: Software Development :: Libraries :: Python Modules
